pipefysdk/__init__.py
pipefysdk/base_service.py
pipefysdk/errors/__init__.py
pipefysdk/errors/card_create_pipefy_error.py
pipefysdk/errors/card_move_pipefy_error.py
pipefysdk/errors/http_request_pipefy_error.py
pipefysdk/errors/permission_error.py
pipefysdk/errors/search_field_pipefy_error.py
pipefysdk/http_client.py
pipefysdk/main.py
pipefysdk/models/__init__.py
pipefysdk/models/models.py
pipefysdk/mutations/__init__.py
pipefysdk/mutations/mutation_cards.py
pipefysdk/queries/__init__.py
pipefysdk/queries/query_cards.py
pipefysdk/queries/query_phases.py
pipefysdk/services/__init__.py
pipefysdk/services/attachment_service.py
pipefysdk/services/card_service.py
pipefysdk/services/email_service.py
pipefysdk/services/organization_service.py
pipefysdk/services/phase_service.py
pipefysdk/services/report_service.py
pipefysdk/utils/__init__.py
pipefysdk/utils/binary_tree.py
pipefysdk/utils/constraints.py
pipefysdk-0.2.3.dist-info/LICENSE
pipefysdk-0.2.3.dist-info/METADATA
pipefysdk-0.2.3.dist-info/WHEEL
pipefysdk-0.2.3.dist-info/RECORD
