Metadata-Version: 2.3
Name: pipefysdk
Version: 0.2.3
Summary: 
Author: itallo.minatti
Author-email: itallominatti@gmail.com
Requires-Python: >=3.11
Classifier: Programming Language :: Python :: 3
Classifier: Programming Language :: Python :: 3.11
Classifier: Programming Language :: Python :: 3.12
Classifier: Programming Language :: Python :: 3.13
Requires-Dist: httpx (>=0.28.1,<0.29.0)
Requires-Dist: pydantic (>=2.10.6,<3.0.0)
